Workbook

Sheet README
A1: GRAIL Collector - CFD dataset rev 4.2 with Stage 3-7 results
A3: Dataset_rev4.2: the 300 GRAIL-CHT cases, copied cell for cell from GRAIL_CFD_dataset_FINAL_rev4.2.csv.
A4: The CSV file itself is unchanged (MD5 13fd464c09a7c26fbe0fa75a5f5113b3, the MD5 recorded by Stage 3).
A5: Nothing was added to, removed from or edited in the 300 rows.
A6: Summary: the headline Stage 3-7 results, each linked to its detail sheet.
A7: Stage3_ANN, Stage5_NSGA2, Stage6_Correlations, Stage7_Annual, Economics: detail sheets.
A9: Colour code
A10: blue = number read from the result file named in the 'Source file' column
A11: black = Excel formula computed in this workbook
A12: green = link to another sheet
A14: Numbers are stored at full precision; the displayed decimals are formatting only.
A15: Source paths are relative to the GRAIL_Collector_Complete_Final package folder.
... A17: DESIGN_REVIEW_REQUIRED: 4 modules stagnate above 420 K; Stage 5 optimum at the flow bound and g_ratio -> 1.

Sheet Summary
A1: GRAIL Stages 3-7 - headline results (every number links to its detail sheet)
A3: Stage | B3: Result | C3: Value | D3: Unit | E3: How it was checked
A4: 3. ANN surrogate | B4: Mean absolute % error in efficiency (60 held-out cases) | C4: =Stage3_ANN!E5 -> 0.13751742 | D4: % | E4: 60 cases never seen in training; GPR slightly more accurate (Stage3_ANN)
A5: 3. ANN surrogate | B5: Efficiency test R2, single ANNs - lowest | C5: =Stage3_ANN!C5 -> 0.99943492 | D5: -
A6: 3. ANN surrogate | B6: Efficiency test R2, single ANNs - highest | C6: =Stage3_ANN!D5 -> 0.99977123 | D6: -
A7: 3. ANN surrogate | B7: GPR efficiency test R2 | C7: =Stage3_ANN!G5 -> 0.99988027 | D7: - | E7: stated in the report
A8: 3. ANN surrogate | B8: SHAP rank 1-4 for efficiency | C8: =Stage3_ANN!B12&", "&Stage3_ANN!B13&", "&Stage3_ANN!B14&", "&Stage3_ANN!B15 -> T_in_K, T_amb_K, mdot_total_kg_s, f_interdig | D8: - | E8: f_interdig = arrangement
A9: 5. NSGA-II | B9: Largest efficiency error of 8 designs re-run in GRAIL-CHT | C9: =Stage5_NSGA2!B13 -> 0.12831784 | D9: points | E9: full GRAIL-CHT re-run
A10: 5. NSGA-II | B10: Largest plate-spread (std) error of the same 8 designs | C10: =Stage5_NSGA2!B14 -> 2.3386815 | D10: %
A11: 6. System model | B11: eta0 alternating | C11: =Stage6_Correlations!B4 -> 0.5965906 | D11: - | E11: 22 GRAIL-CHT runs
A12: 6. System model | B12: a1 alternating | C12: =Stage6_Correlations!B5 -> 2.0038828 | D12: W/m2K
A13: 6. System model | B13: eta0 parallel | C13: =Stage6_Correlations!C4 -> 0.6367728 | D13: -
A14: 6. System model | B14: a1 parallel | C14: =Stage6_Correlations!C5 -> 2.1040764 | D14: W/m2K
A15: 6. System model | B15: Largest error at points left out of the fit | C15: =Stage6_Correlations!B21 -> 0.23863308 | D15: points | E15: tank energy balance closes (1e-12 kWh)
A16: 7. Annual, Berhampur | B16: Sunlight on the collector (POA) | C16: =Stage7_Annual!B5 -> 1976.1349 | D16: kWh/m2/yr
A17: 7. Annual, Berhampur | B17: Yield at 40 C inlet - parallel | C17: =Stage7_Annual!B7 -> 1029.8939 | D17: kWh/m2/yr
A18: 7. Annual, Berhampur | B18: Yield at 40 C inlet - alternating | C18: =Stage7_Annual!B8 -> 965.15688 | D18: kWh/m2/yr
A19: 7. Annual, Berhampur | B19: Weather processing vs PVGIS PV report (35 deg) | C19: =Stage7_Annual!B28 -> -0.015148046 | D19: - | E19: independent PVGIS report
A20: 7. Economics | B20: Best size for 100 L/day at 45 C | C20: =Economics!B8 -> 2 | D20: modules | E20: sizing sweep 1-4 modules
A21: 7. Economics | B21: Solar fraction - parallel | C21: =Economics!B18 -> 0.85838133 | D21: -
A22: 7. Economics | B22: Solar fraction - alternating | C22: =Economics!C18 -> 0.83036277 | D22: -
A23: 7. Economics | B23: Cost of solar heat - parallel | C23: =Economics!B20 -> 4.3393758 | D23: Rs/kWh
A24: 7. Economics | B24: Cost of solar heat - alternating | C24: =Economics!C20 -> 4.4850594 | D24: Rs/kWh
A25: 7. Economics | B25: Cost of heat from an electric geyser | C25: =Economics!B15 -> 4.9473684 | D25: Rs/kWh | E25: tariff / 0.95
A26: 7. Economics | B26: Simple payback - parallel | C26: =Economics!B21 -> 7.3563519 | D26: yr
A27: 7. Economics | B27: Simple payback - alternating | C27: =Economics!C21 -> 7.6403358 | D27: yr
A28: 7. Economics | B28: Tariff (TPSODL domestic, FY 2026-27) | C28: =Economics!B4 -> 4.7 | D28: Rs/kWh | E28: unchanged from FY 2025-26

Sheet Dataset_rev4.2
A1: case_id | B1: geometry_version | C1: solver | D1: arrangement | E1: f_interdig | F1: G_T_W_m2 | G1: T_in_K | H1: T_amb_K | I1: v_wind_m_s | J1: mdot_total_kg_s | K1: mdot_channel_kg_s | L1: bridge_mm | M1: g_ratio | N1: lambda_G | O1: Dh_in_mm | P1: Dh_out_mm | Q1: A_in_mm2 | R1: A_out_mm2 | S1: Re_in | T1: Re_out | U1: mu_Pa_s | V1: dp_channel_Pa | W1: W_pump_W | X1: q_abs_W_m2 | Y1: T_sky_K | Z1: h_wind_W_m2K | AA1: T_out_K | AB1: dT_fluid_K | AC1: Qu_W | AD1: eta | AE1: T_plate_mean_K | AF1: T_plate_max_K | AG1: T_plate_min_K | AH1: plate_spread_K | AI1: plate_std_K | AJ1: P90_K | AK1: P95_K | AL1: P99_K | AM1: R4_K4 | AN1: Tmean_pow4_K4 | AO1: T_R4_K | AP1: Q_solar_W | AQ1: Q_rad_W | AR1: Q_conv_W | AS1: Q_rear_W | AT1: U_L_W_m2K | AU1: T_glass_mean_K | AV1: lateral_bridge_W | AW1: energy_error_pct | AX1: outer_iters | AY1: residual | AZ1: converged | BA1: Nu_closure_input | BB1: Nu_closure_basis | BC1: dataset_rev | BD1: k_model | BE1: outer_cap | BF1: plate_nx | BG1: plate_ny
A2: ALT_000 | B2: GateA_converged_v1 | C2: GRAIL-CHT-1.0 | D2: alternating | E2: 1 | F2: 833.09982 | G2: 292.06544 | H2: 289.5495 | I2: 3.0065092 | J2: 0.0037512718 | K2: 0.00031260599 | L2: 23.829625 | M2: 0.9381792 | N2: 1.9269042 | O2: 5.198875 | P2: 4.8774764 | Q2: 28.056939 | R2: 24.695162 | S2: 68.289116 | T2: 72.788989 | U2: 0.00084823247 | V2: 14.305339 | W2: 5.3824689e-05 | X2: 540.6043 | Y2: 271.97144 | Z2: 17.124735 | AA2: 308.54332 | AB2: 16.477881 | AC2: 258.37838 | AD2: 0.58738819 | AE2: 311.46568 | AF2: 316.34758 | AG2: 299.36647 | AH2: 16.981106 | AI2: 4.0633548 | AJ2: 315.84227 | AK2: 316.05255 | AL2: 316.2492 | AM2: 9.4206487e+09 | AN2: 9.4111088e+09 | AO2: 311.54458 | AP2: 285.43907 | AQ2: 3.0184334 | AR2: 20.889207 | AS2: 3.1528591 | AT2: 2.3385146 | AU2: 288.0701 | AV2: 219.64267 | AW2: 6.8833767e-05 | AX2: 348 | AY2: 9.6885918e-07 | AZ2: True | BA2: 4.48 | BB2: conjugate_3D_benchmark_H1_type | BC2: 4 | BD2: k(T)_cubic_273_373K | BE2: 3000 | BF2: richardson_2x220_minus_110 | BG2: 120
A3: ALT_001 | B3: GateA_converged_v1 | C3: GRAIL-CHT-1.0 | D3: alternating | E3: 1 | F3: 484.53208 | G3: 326.79042 | H3: 287.06705 | I3: 3.3326153 | J3: 0.0028023535 | K3: 0.00023352946 | L3: 20.210867 | M3: 0.67230634 | N3: 0.56264461 | O3: 5.198875 | P3: 3.4952366 | Q3: 28.056939 | R3: 12.681619 | S3: 90.820953 | T3: 135.08865 | U3: 0.00047645809 | V3: 15.515524 | W3: 4.3610816e-05 | X3: 314.41626 | Y3: 268.48134 | Z3: 18.363938 | AA3: 335.8182 | AB3: 9.0277783 | AC3: 105.74993 | AD3: 0.41335542 | AE3: 338.72467 | AF3: 342.11401 | AG3: 330.63219 | AH3: 11.48182 | AI3: 2.8682685 | AJ3: 341.80601 | AK3: 341.93833 | AL3: 342.05809 | AM3: 1.3169609e+10 | AN3: 1.3163983e+10 | AO3: 338.76086 | AP3: 166.01178 | AQ3: 7.4971958 | AR3: 45.332992 | AS3: 7.4314587 | AT3: 2.2093991 | AU3: 287.95244 | AV3: 117.09652 | AW3: 0.0001243856 | AX3: 413 | AY3: 9.9648372e-07 | AZ3: True | BA3: 4.48 | BB3: conjugate_3D_benchmark_H1_type | BC3: 4 | BD3: k(T)_cubic_273_373K | BE3: 3000 | BF3: richardson_2x220_minus_110 | BG3: 120
A4: ALT_002 | B4: GateA_converged_v1 | C4: GRAIL-CHT-1.0 | D4: alternating | E4: 1 | F4: 419.95033 | G4: 290.30437 | H4: 297.28222 | I4: 3.0624161 | J4: 0.0022870718 | K4: 0.00019058932 | L4: 28.382706 | M4: 0.82406358 | N4: 1.4522045 | O4: 5.198875 | P4: 4.2842036 | Q4: 28.056939 | R4: 19.052928 | S4: 38.649435 | T4: 46.901034 | U4: 0.00091374391 | V4: 11.973004 | W4: 2.7465516e-05 | X4: 272.50871 | Y4: 282.93878 | Z4: 17.337181 | AA4: 303.72759 | AB4: 13.423221 | AC4: 128.32546 | AD4: 0.57873663 | AE4: 308.89069 | AF4: 314.22283 | AG4: 296.47764 | AH4: 17.745193 | AI4: 4.5555459 | AJ4: 313.82852 | AK4: 313.99297 | AL4: 314.152 | AM4: 9.1154941e+09 | AN4: 9.1037282e+09 | AO4: 308.99045 | AP4: 143.8846 | AQ4: 1.7944653 | AR4: 12.094493 | AS4: 1.6699932 | AT4: 2.5384971 | AU4: 295.34505 | AV4: 155.24975 | AW4: 0.00013315055 | AX4: 612 | AY4: 9.8032024e-07 | AZ4: True | BA4: 4.48 | BB4: conjugate_3D_benchmark_H1_type | BC4: 4 | BD4: k(T)_cubic_273_373K | BE4: 3000 | BF4: richardson_2x220_minus_110 | BG4: 120
A5: ALT_003 | B5: GateA_converged_v1 | C5: GRAIL-CHT-1.0 | D5: alternating | E5: 1 | F5: 882.51611 | G5: 309.99964 | H5: 296.5432 | I5: 2.4391076 | J5: 0.0023901274 | K5: 0.00019917729 | L5: 24.919449 | M5: 0.66069254 | N5: 1.5280477 | O5: 5.198875 | P5: 3.4348579 | Q5: 28.056939 | R5: 12.247264 | S5: 66.901914 | T5: 101.26028 | U5: 0.00055165855 | V5: 11.262996 | W5: 2.7000999e-05 | X5: 572.67088 | Y5: 281.8844 | Z5: 14.968609 | AA5: 334.66256 | AB5: 24.662918 | AC5: 246.40062 | AD5: 0.52879243 | AE5: 344.28998 | AF5: 354.28054 | AG5: 320.94833 | AH5: 33.332209 | AI5: 8.507699 | AJ5: 353.48462 | AK5: 353.82565 | AL5: 354.13963 | AM5: 1.4101452e+10 | AN5: 1.4050686e+10 | AO5: 344.60055 | AP5: 302.37023 | AQ5: 7.4479161 | AR5: 41.652639 | AS5: 6.8688459 | AT5: 2.2201087 | AU5: 297.63969 | AV5: 300.98542 | AW5: 6.8021623e-05 | AX5: 680 | AY5: 9.9555052e-07 | AZ5: True | BA5: 4.48 | BB5: conjugate_3D_benchmark_H1_type | BC5: 4 | BD5: k(T)_cubic_273_373K | BE5: 3000 | BF5: richardson_2x220_minus_110 | BG5: 120
A6: ALT_004 | B6: GateA_converged_v1 | C6: GRAIL-CHT-1.0 | D6: alternating | E6: 1 | F6: 475.14868 | G6: 302.63575 | H6: 311.73416 | I6: 4.9430841 | J6: 0.0014730988 | K6: 0.00012275824 | L6: 27.529366 | M6: 0.79686898 | N6: 1.9054237 | O6: 5.198875 | P6: 4.1428222 | Q6: 28.056939 | R6: 17.816161 | S6: 35.123905 | T6: 44.077391 | U6: 0.00064761505 | V6: 5.4925203 | W6: 8.1153713e-06 | X6: 308.3273 | Y6: 303.81952 | Z6: 24.48372 | AA6: 324.20915 | AB6: 21.573398 | AC6: 132.83935 | AD6: 0.52949673 | AE6: 336.76881 | AF6: 346.7795 | AG6: 313.38952 | AH6: 33.38998 | AI6: 8.7875141 | AJ6: 346.28453 | AK6: 346.49919 | AL6: 346.69822 | AM6: 1.291427e+10 | AN6: 1.2862562e+10 | AO6: 337.10676 | AP6: 162.79682 | AQ6: 4.1154818 | AR6: 22.240303 | AS6: 3.6014821 | AT6: 2.2663639 | AU6: 311.86003 | AV6: 200.13172 | AW6: 0.00012463165 | AX6: 1085 | AY6: 9.9512295e-07 | AZ6: True | BA6: 4.48 | BB6: conjugate_3D_benchmark_H1_type | BC6: 4 | BD6: k(T)_cubic_273_373K | BE6: 3000 | BF6: richardson_2x220_minus_110 | BG6: 120
A7: ALT_005 | B7: GateA_converged_v1 | C7: GRAIL-CHT-1.0 | D7: alternating | E7: 1 | F7: 602.73567 | G7: 315.6043 | H7: 284.38331 | I7: 3.6742844 | J7: 0.003590308 | K7: 0.00029919233 | L7: 20.987312 | M7: 0.51301612 | N7: 1.8617416 | O7: 5.198875 | P7: 2.6671067 | Q7: 28.056939 | R7: 7.3841807 | S7: 97.804909 | T7: 190.64685 | U7: 0.00056683792 | V7: 26.299442 | W7: 9.4707219e-05 | X7: 391.11939 | Y7: 264.72517 | Z7: 19.662281 | AA7: 325.95181 | AB7: 10.347507 | AC7: 155.29008 | AD7: 0.48795851 | AE7: 328.13016 | AF7: 331.44064 | AG7: 320.03222 | AH7: 11.408426 | AI7: 2.7634129 | AJ7: 331.10592 | AK7: 331.24395 | AL7: 331.37775 | AM7: 1.1597605e+10 | AN7: 1.1592699e+10 | AO7: 328.16487 | AP7: 206.51104 | AQ7: 6.0062358 | AR7: 38.921102 | AS7: 6.2934155 | AT7: 2.2175176 | AU7: 284.53914 | AV7: 141.99929 | AW7: 9.886769e-05 | AX7: 323 | AY7: 9.8158677e-07 | AZ7: True | BA7: 4.48 | BB7: conjugate_3D_benchmark_H1_type | BC7: 4 | BD7: k(T)_cubic_273_373K | BE7: 3000 | BF7: richardson_2x220_minus_110 | BG7: 120
A8: ALT_006 | B8: GateA_converged_v1 | C8: GRAIL-CHT-1.0 | D8: alternating | E8: 1 | F8: 728.74084 | G8: 324.79199 | H8: 305.44469 | I8: 0.23357321 | J8: 0.002006875 | K8: 0.00016723959 | L8: 20.352289 | M8: 0.66768078 | N8: 0.69910539 | O8: 5.198875 | P8: 3.4711889 | Q8: 28.056939 | R8: 12.507717 | S8: 69.948625 | T8: 104.76357 | U8: 0.00044302577 | V8: 9.7989281 | W8: 1.9724397e-05 | X8: 472.88503 | Y8: 294.67137 | Z8: 6.5875782 | AA8: 347.34556 | AB8: 22.553574 | AC8: 189.19601 | AD8: 0.49170537 | AE8: 358.19198 | AF8: 368.1727 | AG8: 334.85551 | AH8: 33.317191 | AI8: 8.5957914 | AJ8: 367.45822 | AK8: 367.75733 | AL8: 368.0488 | AM8: 1.6517329e+10 | AN8: 1.6461274e+10 | AO8: 358.49653 | AP8: 249.6833 | AQ8: 8.835976 | AR8: 44.062878 | AS8: 7.5882192 | AT8: 2.1718507 | AU8: 308.84225 | AV8: 257.72228 | AW8: 8.3393766e-05 | AX8: 835 | AY8: 9.9994611e-07 | AZ8: True | BA8: 4.48 | BB8: conjugate_3D_benchmark_H1_type | BC8: 4 | BD8: k(T)_cubic_273_373K | BE8: 3000 | BF8: richardson_2x220_minus_110 | BG8: 120
A9: ALT_007 | B9: GateA_converged_v1 | C9: GRAIL-CHT-1.0 | D9: alternating | E9: 1 | F9: 874.79088 | G9: 320.13998 | H9: 301.64373 | I9: 4.0851632 | J9: 0.0042354719 | K9: 0.00035295599 | L9: 30.967642 | M9: 0.38238352 | N9: 0.53247066 | O9: 5.198875 | P9: 1.9879641 | Q9: 28.056939 | R9: 4.1024058 | S9: 129.04245 | T9: 337.46866 | U9: 0.00050682384 | V9: 120.75326 | W9: 0.000512986 | X9: 567.65792 | Y9: 289.18818 | Z9: 21.22362 | AA9: 334.70815 | AB9: 14.568169 | AC9: 257.91883 | AD9: 0.55839933 | AE9: 336.87514 | AF9: 340.87145 | AG9: 326.68447 | AH9: 14.18698 | AI9: 3.3594635 | AJ9: 340.48251 | AK9: 340.63427 | AL9: 340.79248 | AM9: 1.2886453e+10 | AN9: 1.2878813e+10 | AO9: 336.92509 | AP9: 299.72338 | AQ9: 5.4611343 | AR9: 31.274807 | AS9: 5.0683853 | AT9: 2.2472929 | AU9: 301.84785 | AV9: 204.05382 | AW9: 7.1783915e-05 | AX9: 304 | AY9: 9.9499613e-07 | AZ9: True | BA9: 4.48 | BB9: conjugate_3D_benchmark_H1_type | BC9: 4 | BD9: k(T)_cubic_273_373K | BE9: 3000 | BF9: richardson_2x220_minus_110 | BG9: 120
A10: ALT_008 | B10: GateA_converged_v1 | C10: GRAIL-CHT-1.0 | D10: alternating | E10: 1 | F10: 551.36012 | G10: 327.31073 | H10: 296.25551 | I10: 2.2553945 | J10: 0.0038415657 | K10: 0.00032013048 | L10: 33.136807 | M10: 0.80074899 | N10: 0.64102689 | O10: 5.198875 | P10: 4.1629939 | Q10: 28.056939 | R10: 17.99008 | S10: 125.21767 | T10: 156.37568 | U10: 0.00047372958 | V10: 12.983916 | W10: 5.0028652e-05 | X10: 357.78144 | Y10: 281.47429 | Z10: 14.270499 | AA10: 336.04165 | AB10: 8.7309221 | AC10: 140.19892 | AD10: 0.48158771 | AE10: 337.6479 | AF10: 340.24026 | AG10: 331.18966 | AH10: 9.050596 | AI10: 2.1838055 | AJ10: 339.99505 | AK10: 340.09401 | AL10: 340.1932 | AM10: 1.3000639e+10 | AN10: 1.2997392e+10 | AO10: 337.66899 | AP10: 188.9086 | AQ10: 6.2471967 | AR10: 36.507986 | AS10: 5.9547034 | AT10: 2.2287477 | AU10: 296.75953 | AV10: 120.63034 | AW10: -0.0001107024 | AX10: 306 | AY10: 9.7648416e-07 | AZ10: True | BA10: 4.48 | BB10: conjugate_3D_benchmark_H1_type | BC10: 4 | BD10: k(T)_cubic_273_373K | BE10: 3000 | BF10: richardson_2x220_minus_110 | BG10: 120
A11: ALT_009 | B11: GateA_converged_v1 | C11: GRAIL-CHT-1.0 | D11: alternating | E11: 1 | F11: 664.23833 | G11: 292.46794 | H11: 311.34424 | I11: 3.0906016 | J11: 0.0018414546 | K11: 0.00015345455 | L11: 26.378164 | M11: 0.90508763 | N11: 1.7020759 | O11: 5.198875 | P11: 4.7054375 | Q11: 28.056939 | R11: 22.983785 | S11: 37.613516 | T11: 41.557873 | U11: 0.00075597063 | V11: 6.6653537 | W11: 1.2310879e-05 | X11: 431.0289 | Y11: 303.24967 | Z11: 17.444286 | AA11: 318.80524 | AB11: 26.337295 | AC11: 202.72554 | AD11: 0.57803031 | AE11: 331.8732 | AF11: 343.53659 | AG11: 304.95679 | AH11: 38.579795 | AI11: 10.070676 | AJ11: 342.81485 | AK11: 343.11128 | AL11: 343.40927 | AM11: 1.2196665e+10 | AN11: 1.213078e+10 | AO11: 332.3229 | AP11: 227.58326 | AQ11: 3.3680831 | AR11: 18.536143 | AS11: 2.9532931 | AT11: 2.293298 | AU11: 311.11301 | AV11: 280.74381 | AW11: 8.8100694e-05 | AX11: 894 | AY11: 9.9296847e-07 | AZ11: True | BA11: 4.48 | BB11: conjugate_3D_benchmark_H1_type | BC11: 4 | BD11: k(T)_cubic_273_373K | BE11: 3000 | BF11: richardson_2x220_minus_110 | BG11: 120
A12: ALT_010 | B12: GateA_converged_v1 | C12: GRAIL-CHT-1.0 | D12: alternating | E12: 1 | F12: 939.24491 | G12: 314.72829 | H12: 300.47437 | I12: 0.28098577 | J12: 0.0020409574 | K12: 0.00017007978 | L12: 30.176335 | M12: 0.4072604 | N12: 1.8042564 | O12: 5.198875 | P12: 2.1172959 | Q12: 28.056939 | R12: 4.6535529 | S12: 64.50706 | T12: 158.39267 | U12: 0.00048855621 | V12: 21.582966 | W12: 4.4182462e-05 | X12: 609.4826 | Y12: 287.50819 | Z12: 6.7677459 | AA12: 344.64062 | AB12: 29.912329 | AC12: 255.18812 | AD12: 0.51457381 | AE12: 358.57625 | AF12: 371.4943 | AG12: 328.53053 | AH12: 42.963762 | AI12: 11.14359 | AJ12: 370.66628 | AK12: 371.00817 | AL12: 371.34402 | AM12: 1.662619e+10 | AN12: 1.6532026e+10 | AO12: 359.08576 | AP12: 321.80681 | AQ12: 9.6159262 | AR12: 48.644025 | AS12: 8.3585294 | AT12: 2.1715607 | AU12: 304.09571 | AV12: 341.28983 | AW12: 6.4713985e-05 | AX12: 841 | AY12: 9.9603801e-07 | AZ12: True | BA12: 4.48 | BB12: conjugate_3D_benchmark_H1_type | BC12: 4 | BD12: k(T)_cubic_273_373K | BE12: 3000 | BF12: richardson_2x220_minus_110 | BG12: 120
A13: ALT_011 | B13: GateA_converged_v1 | C13: GRAIL-CHT-1.0 | D13: alternating | E13: 1 | F13: 434.88212 | G13: 320.91009 | H13: 291.07782 | I13: 1.1652801 | J13: 0.0040721814 | K13: 0.00033934845 | L13: 20.339255 | M13: 0.85670799 | N13: 1.0130279 | O13: 5.198875 | P13: 4.4539177 | Q13: 28.056939 | R13: 20.59235 | S13: 117.22826 | T13: 136.83573 | U13: 0.00053639242 | V13: 12.314168 | W13: 5.0296415e-05 | X13: 282.19805 | Y13: 274.1276 | Z13: 10.128064 | AA13: 327.08611 | AB13: 6.1760206 | AC13: 105.12648 | AD13: 0.45783254 | AE13: 328.10683 | AF13: 329.92463 | AG13: 323.54534 | AH13: 6.3792903 | AI13: 1.5131741 | AJ13: 329.73125 | AK13: 329.81191 | AL13: 329.88696 | AM13: 1.1590878e+10 | AN13: 1.1589404e+10 | AO13: 328.11726 | AP13: 149.00057 | AQ13: 5.2821424 | AR13: 33.265168 | AS13: 5.3269886 | AT13: 2.2440478 | AU13: 290.85037 | AV13: 87.173758 | AW13: -0.00013869972 | AX13: 315 | AY13: 9.8280589e-07 | AZ13: True | BA13: 4.48 | BB13: conjugate_3D_benchmark_H1_type | BC13: 4 | BD13: k(T)_cubic_273_373K | BE13: 3000 | BF13: richardson_2x220_minus_110 | BG13: 120
... A301: PAR_149 | B301: GateA_converged_v1 | C301: GRAIL-CHT-1.0 | D301: parallel | E301: 0 | F301: 587.40932 | G301: 297.3369 | H301: 305.31977 | I301: 1.0410317 | J301: 0.0027200694 | K301: 0.00022667245 | L301: 26.316325 | M301: 0.69223154 | N301: 1.359485 | O301: 5.198875 | P301: 3.5988252 | Q301: 28.056939 | R301: 13.44445 | S301: 55.854896 | T301: 80.688171 | U301: 0.00075198051 | V301: 16.594705 | W301: 4.5274573e-05 | X301: 381.17402 | Y301: 294.49062 | Z301: 9.6559204 | AA301: 314.51126 | AB301: 17.174362 | AC301: 195.27061 | AD301: 0.62959624 | AE301: 307.67773 | AF301: 315.34868 | AG301: 299.48326 | AH301: 15.865413 | AI301: 4.8243466 | AJ301: 314.37291 | AK301: 314.98015 | AL301: 315.29634 | AM301: 8.9747857e+09 | AN301: 8.9615729e+09 | AO301: 307.79107 | AP301: 201.25988 | AQ301: 0.75607717 | AR301: 4.8940246 | AS301: 0.33921617 | AT301: 4.8106448 | AU301: 302.1965 | AV301: 7.8493372e-11 | AW301: -2.2681162e-05 | AX301: 134 | AY301: 9.0482615e-07 | AZ301: True | BA301: 4.48 | BB301: conjugate_3D_benchmark_H1_type | BC301: 4 | BD301: k(T)_cubic_273_373K | BE301: 3000 | BF301: richardson_2x220_minus_110 | BG301: 120

Sheet Stage3_ANN
A1: Stage 3 - ANN surrogate (10-seed MLP ensemble) vs GPR and linear baseline
A2: Train 240 cases / test 60 held-out cases; inputs: G_T_W_m2, T_in_K, T_amb_K, v_wind_m_s, mdot_total_kg_s, bridge_mm, g_ratio, lambda_G, f_interdig
A4: Target | B4: ANN ensemble test R2 | C4: Single-ANN test R2 min | D4: Single-ANN test R2 max | E4: ANN test MAPE (%) | F4: ANN test RMSE | G4: GPR test R2 | H4: Linear test R2 | I4: Best hidden layers | J4: Source file
A5: eta | B5: 0.99974687 | C5: 0.99943492 | D5: 0.99977123 | E5: 0.13751742 | F5: 0.00099745586 | G5: 0.99988027 | H5: 0.88971386 | I5: [64, 32] | J5: 12_Stages_3-5-6-7/surrogate/stage3_report.json
A6: plate_std_K | B6: 0.99958959 | C6: 0.99858685 | D6: 0.99968659 | E6: 0.53010409 | F6: 0.07267792 | G6: 0.99996271 | H6: 0.85187402 | I6: [32, 32] | J6: 12_Stages_3-5-6-7/surrogate/stage3_report.json
A7: log_dp_Pa | B7: 0.99978728 | C7: 0.99950269 | D7: 0.99981875 | E7: 0.92367875 | F7: 0.014784902 | G7: 0.99998458 | H7: 0.97473624 | I7: [64, 32] | J7: 12_Stages_3-5-6-7/surrogate/stage3_report.json
A8: T_plate_mean_K | B8: 0.99943918 | C8: 0.99918689 | D8: 0.99957793 | E8: 0.059502447 | F8: 0.4524918 | G8: 0.99999107 | H8: 0.88130153 | I8: [64, 32] | J8: 12_Stages_3-5-6-7/surrogate/stage3_report.json
A10: SHAP mean |SHAP| on the test set (efficiency eta), ranked
A11: Rank | B11: Input | C11: mean |SHAP| (eta) | D11: Source file
A12: 1 | B12: T_in_K | C12: 0.033826985 | D12: 12_Stages_3-5-6-7/surrogate/stage3_report.json
A13: 2 | B13: T_amb_K | C13: 0.023449581 | D13: 12_Stages_3-5-6-7/surrogate/stage3_report.json
A14: 3 | B14: mdot_total_kg_s | C14: 0.022426688 | D14: 12_Stages_3-5-6-7/surrogate/stage3_report.json
A15: 4 | B15: f_interdig | C15: 0.019163461 | D15: 12_Stages_3-5-6-7/surrogate/stage3_report.json
A16: 5 | B16: G_T_W_m2 | C16: 0.009465091 | D16: 12_Stages_3-5-6-7/surrogate/stage3_report.json
A17: 6 | B17: v_wind_m_s | C17: 0.0004695086 | D17: 12_Stages_3-5-6-7/surrogate/stage3_report.json
A18: 7 | B18: bridge_mm | C18: 0.00011612576 | D18: 12_Stages_3-5-6-7/surrogate/stage3_report.json
A19: 8 | B19: g_ratio | C19: 6.9845044e-05 | D19: 12_Stages_3-5-6-7/surrogate/stage3_report.json
A20: 9 | B20: lambda_G | C20: 6.1009409e-05 | D20: 12_Stages_3-5-6-7/surrogate/stage3_report.json

Sheet Stage5_NSGA2
A1: Stage 5 - NSGA-II optimum points re-run in GRAIL-CHT (surrogate vs full model)
A3: arrangement | B3: pick | C3: eta_ann | D3: eta_cht | E3: std_ann | F3: std_cht | G3: dp_ann | H3: dp_cht | I3: Tmax_cht | J3: converged | K3: eta_err_pp | L3: std_err_pct | M3: dp_err_pct | N3: |eta err| (points) | O3: |plate std err| (%) | P3: Source file
A4: alternating | B4: max_eta | C4: 0.57833968 | D4: 0.57840459 | E4: 2.872148 | F4: 2.8337361 | G4: 11.349513 | H4: 10.731234 | I4: 331.16749 | J4: =TRUE() -> TRUE | K4: -0.0064912199 | L4: 1.3555203 | M4: 5.7614994 | N4: =ABS(K4) -> 0.0064912199 | O4: =ABS(L4) -> 1.3555203 | P4: 12_Stages_3-5-6-7/optimisation/verification_vs_GRAIL-CHT.csv
A5: alternating | B5: min_std | C5: 0.57734771 | D5: 0.578167 | E5: 2.827119 | F5: 2.866042 | G5: 20.186823 | H5: 20.179551 | I5: 331.27217 | J5: =TRUE() -> TRUE | K5: -0.081928876 | L5: -1.3580747 | M5: 0.036033918 | N5: =ABS(K5) -> 0.081928876 | O5: =ABS(L5) -> 1.3580747 | P5: 12_Stages_3-5-6-7/optimisation/verification_vs_GRAIL-CHT.csv
A6: alternating | B6: knee | C6: 0.55993348 | D6: 0.56014255 | E6: 4.8000842 | F6: 4.8160331 | G6: 7.5064685 | H6: 7.5471429 | I6: 340.34176 | J6: =TRUE() -> TRUE | K6: -0.02090638 | L6: -0.33116291 | M6: -0.53893761 | N6: =ABS(K6) -> 0.02090638 | O6: =ABS(L6) -> 0.33116291 | P6: 12_Stages_3-5-6-7/optimisation/verification_vs_GRAIL-CHT.csv
A7: parallel | B7: max_eta | C7: 0.5939989 | D7: 0.59432495 | E7: 3.713035 | F7: 3.7626445 | G7: 11.261201 | H7: 10.697313 | I7: 327.82804 | J7: =TRUE() -> TRUE | K7: -0.032605384 | L7: -1.318476 | M7: 5.271309 | N7: =ABS(K7) -> 0.032605384 | O7: =ABS(L7) -> 1.318476 | P7: 12_Stages_3-5-6-7/optimisation/verification_vs_GRAIL-CHT.csv
A8: parallel | B8: min_std | C8: 0.5930673 | D8: 0.59435048 | E8: 3.6752121 | F8: 3.7632218 | G8: 10.634513 | H8: 10.665826 | I8: 327.81822 | J8: =TRUE() -> TRUE | K8: -0.12831784 | L8: -2.3386815 | M8: -0.29358028 | N8: =ABS(K8) -> 0.12831784 | O8: =ABS(L8) -> 2.3386815 | P8: 12_Stages_3-5-6-7/optimisation/verification_vs_GRAIL-CHT.csv
A9: parallel | B9: knee | C9: 0.58518298 | D9: 0.58497766 | E9: 5.6382095 | F9: 5.6429581 | G9: 6.5598002 | H9: 6.6061083 | I9: 334.27921 | J9: =TRUE() -> TRUE | K9: 0.020531727 | L9: -0.084150203 | M9: -0.70098901 | N9: =ABS(K9) -> 0.020531727 | O9: =ABS(L9) -> 0.084150203 | P9: 12_Stages_3-5-6-7/optimisation/verification_vs_GRAIL-CHT.csv
A10: alternating | B10: as_built | C10: 0.54671504 | D10: 0.54658208 | E10: 6.2946993 | F10: 6.2718879 | G10: 23.813981 | H10: 23.857855 | I10: 347.02929 | J10: =TRUE() -> TRUE | K10: 0.013295633 | L10: 0.36370901 | M10: -0.18389724 | N10: =ABS(K10) -> 0.013295633 | O10: =ABS(L10) -> 0.36370901 | P10: 12_Stages_3-5-6-7/optimisation/verification_vs_GRAIL-CHT.csv
A11: parallel | B11: as_built | C11: 0.58337915 | D11: 0.5829583 | E11: 6.0017879 | F11: 6.0103983 | G11: 23.581325 | H11: 23.589261 | I11: 335.59759 | J11: =TRUE() -> TRUE | K11: 0.042084254 | L11: -0.1432591 | M11: -0.033640886 | N11: =ABS(K11) -> 0.042084254 | O11: =ABS(L11) -> 0.1432591 | P11: 12_Stages_3-5-6-7/optimisation/verification_vs_GRAIL-CHT.csv
A13: Largest |eta error| (points) | B13: =MAX(N4:N11) -> 0.12831784
A14: Largest |plate std error| (%) | B14: =MAX(O4:O11) -> 2.3386815
A16: DESIGN_REVIEW_REQUIRED: the optimum sits at the flow upper bound and at g_ratio -> 1.0.

Sheet Stage6_Correlations
A1: Stage 6 - ISO 9806 steady-state efficiency, q = eta0 G - a1 dT - a2 dT^2 (dT = Tm - Ta)
A3: Quantity | B3: Alternating | C3: Parallel | D3: Unit | E3: Source file
A4: eta0 | B4: 0.5965906 | C4: 0.6367728 | D4: - | E4: 12_Stages_3-5-6-7/system_model/efficiency_correlations.json
A5: a1 | B5: 2.0038828 | C5: 2.1040764 | D5: W/m2K | E5: 12_Stages_3-5-6-7/system_model/efficiency_correlations.json
A6: a2 | B6: 0.00037944759 | C6: 0 | D6: W/m2K2 | E6: 12_Stages_3-5-6-7/system_model/efficiency_correlations.json
A7: Fit RMS error | B7: 0.15079148 | C7: 0.22889514 | D7: points | E7: 12_Stages_3-5-6-7/system_model/efficiency_correlations.json
A8: Fit max error | B8: 0.31825874 | C8: 0.43389485 | D8: points | E8: 12_Stages_3-5-6-7/system_model/efficiency_correlations.json
A9: a2 constraint | B9: not active | C9: a2 >= 0 enforced | E9: 12_Stages_3-5-6-7/system_model/efficiency_correlations.json
A10: Unconstrained a2 (parallel) | C10: -0.00061383567 | D10: W/m2K2 | E10: negative (unphysical), so refitted with a2 = 0; both fits on record
A12: Held-out GRAIL-CHT points (not used in the fit)
A13: Arrangement | B13: G | C13: T_in | D13: T_amb | E13: wind | F13: eta_cht | G13: eta_fit | H13: err_pp | I13: |error| (points) | J13: Source file
A14: alternating | B14: 900 | C14: 323.15 | D14: 303.15 | E14: 0.5 | F14: 0.529666 | G14: 0.52727967 | H14: 0.23863308 | I14: =ABS(H14) -> 0.23863308 | J14: 12_Stages_3-5-6-7/system_model/efficiency_correlations.json
A15: alternating | B15: 900 | C15: 323.15 | D15: 303.15 | E15: 4.9 | F15: 0.52727494 | G15: 0.527391 | H15: -0.011606594 | I15: =ABS(H15) -> 0.011606594 | J15: 12_Stages_3-5-6-7/system_model/efficiency_correlations.json
A16: alternating | B16: 700 | C16: 332.15 | D16: 288.15 | E16: 3 | F16: 0.45002989 | G16: 0.44849795 | H16: 0.15319417 | I16: =ABS(H16) -> 0.15319417 | J16: 12_Stages_3-5-6-7/system_model/efficiency_correlations.json
A17: parallel | B17: 900 | C17: 323.15 | D17: 303.15 | E17: 0.5 | F17: 0.56425578 | G17: 0.56274885 | H17: 0.15069254 | I17: =ABS(H17) -> 0.15069254 | J17: 12_Stages_3-5-6-7/system_model/efficiency_correlations.json
A18: parallel | B18: 900 | C18: 323.15 | D18: 303.15 | E18: 4.9 | F18: 0.56381953 | G18: 0.56276993 | H18: 0.10496002 | I18: =ABS(H18) -> 0.10496002 | J18: 12_Stages_3-5-6-7/system_model/efficiency_correlations.json
A19: parallel | B19: 700 | C19: 332.15 | D19: 288.15 | E19: 3 | F19: 0.48085651 | G19: 0.48128 | H19: -0.042348984 | I19: =ABS(H19) -> 0.042348984 | J19: 12_Stages_3-5-6-7/system_model/efficiency_correlations.json
A21: Largest held-out error (points) | B21: =MAX(I14:I19) -> 0.23863308
A22: Fit based on 22 GRAIL-CHT runs (G 500/900 W/m2 x 4 inlet temperatures, both arrangements) plus these held-out points.

Sheet Stage7_Annual
A1: Stage 7 - Annual performance, Berhampur (PVGIS TMY 2005-2023, tilt 19.3 deg S, Hay-Davies)
A3: Quantity | B3: Value | C3: Unit | D3: Source file
A4: Global horizontal irradiation (GHI) | B4: 1864.9298 | C4: kWh/m2/yr | D4: 12_Stages_3-5-6-7/annual/stage7_results.json
A5: Plane-of-array irradiation (POA) | B5: 1976.1349 | C5: kWh/m2/yr | D5: 12_Stages_3-5-6-7/annual/stage7_results.json
A6: POA after incidence-angle losses | B6: 1854.735 | C6: kWh/m2/yr | D6: 12_Stages_3-5-6-7/annual/stage7_results.json
A7: Collector yield, 40 C (313.15 K) inlet - parallel | B7: 1029.8939 | C7: kWh/m2/yr | D7: 12_Stages_3-5-6-7/annual/stage7_results.json
A8: Collector yield, 40 C (313.15 K) inlet - alternating | B8: 965.15688 | C8: kWh/m2/yr | D8: 12_Stages_3-5-6-7/annual/stage7_results.json
A9: Collector yield, 60 C (333.15 K) inlet - parallel | B9: 882.4596 | C9: kWh/m2/yr | D9: 12_Stages_3-5-6-7/annual/stage7_results.json
A10: Collector yield, 60 C (333.15 K) inlet - alternating | B10: 823.38244 | C10: kWh/m2/yr | D10: 12_Stages_3-5-6-7/annual/stage7_results.json
A12: Weather cross-check at 35 deg tilt against the PVGIS PV report (PVGIS-ERA5)
A13: Month | B13: PVGIS H(i)_m (kWh/m2) | D13: Source file
A14: 1 | B14: 204.15 | D14: 12_Stages_3-5-6-7/annual/weather/PVGIS_PVreport_35deg_crosscheck.csv
A15: 2 | B15: 191.88 | D15: 12_Stages_3-5-6-7/annual/weather/PVGIS_PVreport_35deg_crosscheck.csv
A16: 3 | B16: 204.32 | D16: 12_Stages_3-5-6-7/annual/weather/PVGIS_PVreport_35deg_crosscheck.csv
A17: 4 | B17: 183.05 | D17: 12_Stages_3-5-6-7/annual/weather/PVGIS_PVreport_35deg_crosscheck.csv
A18: 5 | B18: 165.31 | D18: 12_Stages_3-5-6-7/annual/weather/PVGIS_PVreport_35deg_crosscheck.csv
A19: 6 | B19: 122.77 | D19: 12_Stages_3-5-6-7/annual/weather/PVGIS_PVreport_35deg_crosscheck.csv
A20: 7 | B20: 110.99 | D20: 12_Stages_3-5-6-7/annual/weather/PVGIS_PVreport_35deg_crosscheck.csv
A21: 8 | B21: 120.04 | D21: 12_Stages_3-5-6-7/annual/weather/PVGIS_PVreport_35deg_crosscheck.csv
A22: 9 | B22: 132.93 | D22: 12_Stages_3-5-6-7/annual/weather/PVGIS_PVreport_35deg_crosscheck.csv
A23: 10 | B23: 165.15 | D23: 12_Stages_3-5-6-7/annual/weather/PVGIS_PVreport_35deg_crosscheck.csv
A24: 11 | B24: 176.26 | D24: 12_Stages_3-5-6-7/annual/weather/PVGIS_PVreport_35deg_crosscheck.csv
A25: 12 | B25: 188.42 | D25: 12_Stages_3-5-6-7/annual/weather/PVGIS_PVreport_35deg_crosscheck.csv
A26: PVGIS year (sum) | B26: =SUM(B14:B25) -> 1965.27 | C26: kWh/m2/yr
A27: This model at 35 deg | B27: 1935.5 | C27: kWh/m2/yr | D27: 12_Stages_3-5-6-7/annual/stage7_weather_check.txt (tilt 35 line)
A28: Difference | B28: =B27/B26-1 -> -0.015148046
A30: SDHW sizing sweep: 100 L/day delivered at 45 C (318.15 K)
A31: arrangement | B31: n_modules | C31: aperture_m2 | D31: solar_fraction | E31: Q_solar_kWh | F31: yield_kWh_m2 | G31: tank_loss_kWh | H31: hours_tank_limit | I31: max_collector_K | J31: hours_collector_above_393K | K31: capex_Rs | L31: net_saving_Rs | M31: simple_payback_yr | N31: discounted_payback_yr | O31: NPV_Rs | P31: LCOH_Rs_kWh | Q31: Source file
A32: alternating | B32: 1 | C32: 0.528 | D32: 0.50045666 | E32: 384.77673 | F32: 728.7438 | G32: 110.81287 | H32: 0 | I32: 329.04985 | J32: 0 | K32: 16500 | L32: 1523.0397 | M32: 10.833598 | N32: 27 | O32: -3463.5741 | P32: 5.9990115 | Q32: 12_Stages_3-5-6-7/annual/sizing_sweep.csv
A33: alternating | B33: 2 | C33: 1.056 | D33: 0.83036277 | E33: 638.42545 | F33: 604.56956 | G33: 241.52982 | H33: 0 | I33: 349.08008 | J33: 0 | K33: 21000 | L33: 2748.5703 | M33: 7.6403358 | N33: 13 | O33: 2526.3289 | P33: 4.4850594 | Q33: 12_Stages_3-5-6-7/annual/sizing_sweep.csv
A34: alternating | B34: 3 | C34: 1.584 | D34: 0.9474804 | E34: 728.47149 | F34: 459.89362 | G34: 402.22789 | H34: 75 | I34: 389.3622 | J34: 0 | K34: 25500 | L34: 3168.3618 | M34: 8.0483234 | N34: 14 | O34: 1619.525 | P34: 4.687635 | Q34: 12_Stages_3-5-6-7/annual/sizing_sweep.csv
A35: alternating | B35: 4 | C35: 2.112 | D35: 0.97913451 | E35: 752.80879 | F35: 356.44355 | G35: 508.78409 | H35: 533 | I35: 426.59011 | J35: 270 | K35: 30000 | L35: 3274.0624 | M35: 9.1629287 | N35: 18 | O35: -1975.7329 | P35: 5.2539854 | Q35: 12_Stages_3-5-6-7/annual/sizing_sweep.csv
A36: parallel | B36: 1 | C36: 0.528 | D36: 0.53171715 | E36: 408.8114 | F36: 774.26401 | G36: 118.15439 | H36: 0 | I36: 330.78837 | J36: 0 | K36: 16500 | L36: 1640.1691 | M36: 10.059938 | N36: 22 | O36: -2461.0073 | P36: 5.6506716 | Q36: 12_Stages_3-5-6-7/annual/sizing_sweep.csv
A37: parallel | B37: 2 | C37: 1.056 | D37: 0.85838133 | E37: 659.96756 | F37: 624.96928 | G37: 266.45002 | H37: 0 | I37: 353.15858 | J37: 0 | K37: 21000 | L37: 2854.6758 | M37: 7.3563519 | N37: 12 | O37: 3434.537 | P37: 4.3393758 | Q37: 12_Stages_3-5-6-7/annual/sizing_sweep.csv
A38: parallel | B38: 3 | C38: 1.584 | D38: 0.95972971 | E38: 737.88938 | F38: 465.83926 | G38: 435.70726 | H38: 197 | I38: 405.36129 | J38: 29 | K38: 25500 | L38: 3219.0457 | M38: 7.9216023 | N38: 14 | O38: 2053.3534 | P38: 4.6222623 | Q38: 12_Stages_3-5-6-7/annual/sizing_sweep.csv
A39: parallel | B39: 4 | C39: 2.112 | D39: 0.98430907 | E39: 756.78726 | F39: 358.3273 | G39: 533.32454 | H39: 726 | I39: 441.51276 | J39: 486 | K39: 30000 | L39: 3300.7025 | M39: 9.0889742 | N39: 17 | O39: -1747.7073 | P39: 5.2171719 | Q39: 12_Stages_3-5-6-7/annual/sizing_sweep.csv
A41: DESIGN_REVIEW_REQUIRED: with 4 modules the collector stagnates above 420 K (max_collector_K).

Sheet Economics
A1: Economics - 2-module system (1.056 m2), 100 L/day at 45 C, Berhampur
A3: Input | B3: Value | C3: Unit | D3: Basis / source
A4: Electricity tariff | B4: 4.7 | C4: Rs/kWh | D4: TPSODL LT domestic 51-200 kWh/month slab, 470 paise/kWh (FY 2025-26, retained FY 2026-27); electricity duty excluded (conservative)
A5: Electric geyser efficiency | B5: 0.95 | C5: - | D5: 12_Stages_3-5-6-7/annual/stage7_results.json
A6: Capex fixed part | B6: 12000 | C6: Rs | D6: ENGINEERING_ASSUMPTION (Stage 7 sizing sweep)
A7: Capex per module | B7: 4500 | C7: Rs/module | D7: ENGINEERING_ASSUMPTION (Stage 7 sizing sweep)
A8: Modules | B8: 2 | C8: - | D8: best size from the sizing sweep
A9: Life | B9: 15 | C9: yr | D9: 12_Stages_3-5-6-7/annual/stage7_results.json
A10: Discount rate | B10: 0.08 | C10: - | D10: 12_Stages_3-5-6-7/annual/stage7_results.json
A11: O&M per year (fraction of capex) | B11: 0.01 | C11: - | D11: 12_Stages_3-5-6-7/annual/stage7_results.json
A13: Capex (formula) | B13: =B6+B7*B8 -> 21000 | C13: Rs | D13: 12,000 + 4,500 per module; checked against capex_Rs in the sizing sweep below
A14: Capex check vs sizing sweep | B14: =IF(B13=Stage7_Annual!K37,"OK","MISMATCH") -> OK
A15: Cost of heat from an electric geyser | B15: =B4/B5 -> 4.9473684 | C15: Rs/kWh | D15: tariff / geyser efficiency
A17: Result (2 modules) | B17: Parallel | C17: Alternating | D17: Unit
A18: Solar fraction | B18: =Stage7_Annual!D37 -> 0.85838133 | C18: =Stage7_Annual!D33 -> 0.83036277 | D18: -
A19: Solar heat delivered | B19: =Stage7_Annual!E37 -> 659.96756 | C19: =Stage7_Annual!E33 -> 638.42545 | D19: kWh/yr
A20: Cost of solar heat (LCOH) | B20: =Stage7_Annual!P37 -> 4.3393758 | C20: =Stage7_Annual!P33 -> 4.4850594 | D20: Rs/kWh
A21: Simple payback | B21: =Stage7_Annual!M37 -> 7.3563519 | C21: =Stage7_Annual!M33 -> 7.6403358 | D21: yr
A22: Discounted payback | B22: =Stage7_Annual!N37 -> 12 | C22: =Stage7_Annual!N33 -> 13 | D22: yr
A23: Net saving per year | B23: =Stage7_Annual!L37 -> 2854.6758 | C23: =Stage7_Annual!L33 -> 2748.5703 | D23: Rs/yr
A24: NPV over life | B24: =Stage7_Annual!O37 -> 3434.537 | C24: =Stage7_Annual!O33 -> 2526.3289 | D24: Rs
A25: Solar heat cheaper than the geyser? | B25: =IF(B20<B15,"yes","no") -> yes | C25: =IF(C20<B15,"yes","no") -> yes
